accurate_hijri/__init__.py
accurate_hijri/converter.py
accurate_hijri/data/__init__.py
accurate_hijri/data/umm_al_qura.csv
accurate_hijri-0.1.3.dist-info/licenses/LICENSE
accurate_hijri-0.1.3.dist-info/METADATA
accurate_hijri-0.1.3.dist-info/WHEEL
accurate_hijri-0.1.3.dist-info/top_level.txt
accurate_hijri-0.1.3.dist-info/RECORD
