Metadata-Version: 2.4
Name: accurate-hijri
Version: 0.1.3
Summary: Accurate Hijri-Gregorian converter using Umm al-Qura calendar data
Home-page: https://github.com/Samreen-Kazi/accurate-hijri
Author: Samreen Kazi
Classifier: Programming Language :: Python :: 3
Classifier: License :: OSI Approved :: MIT License
Classifier: Operating System :: OS Independent
Classifier: Topic :: Software Development :: Libraries :: Python Modules
Requires-Python: >=3.7
License-File: LICENSE
Dynamic: author
Dynamic: classifier
Dynamic: description
Dynamic: description-content-type
Dynamic: home-page
Dynamic: license-file
Dynamic: requires-python
Dynamic: summary
